whisk_parser/__init__.py
whisk_parser-1.0.0.dist-info/LICENSE.txt
whisk_parser-1.0.0.dist-info/METADATA
whisk_parser-1.0.0.dist-info/WHEEL
whisk_parser-1.0.0.dist-info/top_level.txt
whisk_parser-1.0.0.dist-info/RECORD
