Metadata-Version: 2.1
Name: whisk-parser
Version: 1.0.0
Summary: Parse emails from Vosk API and Whisper.
Home-page: https://github.com/Neuri-ai/whisk-parser
Author: Neuri
Author-email: support@neuri.ai
License: Apache License
Keywords: parse,emails,vosk,whisper,englishspanish
Classifier: Intended Audience :: Developers
Classifier: Programming Language :: Python
Classifier: Programming Language :: Python :: 3
Classifier: Programming Language :: Python :: 3.6
Classifier: Programming Language :: Python :: 3.7
Classifier: Programming Language :: Python :: 3.8
Classifier: Programming Language :: Python :: 3.9
Classifier: Programming Language :: Python :: 3.10
Classifier: Programming Language :: Python :: 3.11
License-File: LICENSE.txt
